tree_sitter_cylc/binding.c
tree_sitter_cylc/__init__.pyi
tree_sitter_cylc/__init__.py
tree_sitter_cylc/py.typed
tree_sitter_cylc/_binding.abi3.so
tree_sitter_cylc/queries/injections.scm
tree_sitter_cylc/queries/highlights.scm
tree_sitter_cylc/queries/README.md
tree_sitter_cylc-0.2.0.dist-info/RECORD
tree_sitter_cylc-0.2.0.dist-info/METADATA
tree_sitter_cylc-0.2.0.dist-info/LICENSE
tree_sitter_cylc-0.2.0.dist-info/WHEEL
tree_sitter_cylc-0.2.0.dist-info/top_level.txt
