Metadata-Version: 2.1
Name: tree-sitter-cylc
Version: 0.2.0
Summary: Cylc grammar for tree-sitter
License: MIT
Project-URL: Homepage, https://github.com/elliotfontaine/tree-sitter-cylc
Keywords: incremental,parsing,tree-sitter,cylc
Classifier: Intended Audience :: Developers
Classifier: License :: OSI Approved :: MIT License
Classifier: Operating System :: OS Independent
Classifier: Topic :: Scientific/Engineering :: Atmospheric Science
Classifier: Topic :: Software Development :: Compilers
Classifier: Topic :: Text Processing :: Linguistic
Classifier: Typing :: Typed
Requires-Python: >=3.9
License-File: LICENSE
Provides-Extra: core
Requires-Dist: tree-sitter~=0.22; extra == "core"
